{
    "name": "munsell/m_10RP5_4",
    "type": "REFLECTANCE_NATURAL",
    "type_max": 1,
    "start_nm": 400,
    "end_nm": 700,
    "resolution": 5,
    "data": [
        0.1748,
        0.1782,
        0.1787,
        0.1749,
        0.1713,
        0.1689,
        0.1647,
        0.1641,
        0.1636,
        0.161,
        0.1584,
        0.1579,
        0.1588,
        0.1582,
        0.159,
        0.156,
        0.1519,
        0.146,
        0.1401,
        0.1386,
        0.138,
        0.1375,
        0.1359,
        0.1322,
        0.1303,
        0.1246,
        0.1244,
        0.1246,
        0.1272,
        0.1341,
        0.1426,
        0.1493,
        0.153,
        0.1582,
        0.1669,
        0.1848,
        0.2067,
        0.2244,
        0.2358,
        0.245,
        0.2471,
        0.2482,
        0.2495,
        0.2501,
        0.2479,
        0.2476,
        0.2493,
        0.246,
        0.2465,
        0.2457,
        0.2433,
        0.2443,
        0.2436,
        0.2432,
        0.2418,
        0.2427,
        0.2435,
        0.2412,
        0.2434,
        0.2426,
        0.2407
    ]
}