{
    "name": "munsell/m_2.5PB2.5_4",
    "type": "REFLECTANCE_NATURAL",
    "type_max": 1,
    "start_nm": 400,
    "end_nm": 700,
    "resolution": 5,
    "data": [
        0.0572,
        0.058,
        0.0604,
        0.059,
        0.0617,
        0.063,
        0.0655,
        0.0689,
        0.0713,
        0.076,
        0.0795,
        0.0847,
        0.0891,
        0.0957,
        0.1023,
        0.103,
        0.1062,
        0.1017,
        0.0972,
        0.0909,
        0.0838,
        0.0763,
        0.069,
        0.0626,
        0.0561,
        0.0501,
        0.046,
        0.0406,
        0.0404,
        0.037,
        0.0368,
        0.0338,
        0.0277,
        0.0331,
        0.0359,
        0.0335,
        0.0352,
        0.0356,
        0.036,
        0.0357,
        0.0368,
        0.0389,
        0.0365,
        0.0381,
        0.0383,
        0.038,
        0.0391,
        0.039,
        0.0401,
        0.0396,
        0.0415,
        0.0409,
        0.0394,
        0.0397,
        0.0406,
        0.0423,
        0.0412,
        0.0407,
        0.0418,
        0.0428,
        0.042
    ]
}