{
    "name": "munsell/m_5PB5_8",
    "type": "REFLECTANCE_NATURAL",
    "type_max": 1,
    "start_nm": 400,
    "end_nm": 700,
    "resolution": 5,
    "data": [
        0.2644,
        0.2987,
        0.3188,
        0.3271,
        0.3302,
        0.3367,
        0.3403,
        0.3453,
        0.3513,
        0.3552,
        0.356,
        0.355,
        0.3526,
        0.3457,
        0.3447,
        0.3355,
        0.323,
        0.3075,
        0.2923,
        0.2767,
        0.263,
        0.2518,
        0.2388,
        0.2209,
        0.209,
        0.196,
        0.1895,
        0.1793,
        0.1713,
        0.1622,
        0.1519,
        0.1404,
        0.1231,
        0.1246,
        0.1217,
        0.1202,
        0.1184,
        0.1186,
        0.1151,
        0.1165,
        0.1149,
        0.112,
        0.1127,
        0.1111,
        0.1149,
        0.1181,
        0.1221,
        0.1284,
        0.1338,
        0.1406,
        0.1442,
        0.1503,
        0.151,
        0.148,
        0.1482,
        0.143,
        0.141,
        0.1338,
        0.1363,
        0.1348,
        0.1373
    ]
}