{
    "name": "munsell/m_5RP8_6",
    "type": "REFLECTANCE_NATURAL",
    "type_max": 1,
    "start_nm": 400,
    "end_nm": 700,
    "resolution": 5,
    "data": [
        0.3787,
        0.4685,
        0.5193,
        0.5337,
        0.537,
        0.5288,
        0.5282,
        0.5242,
        0.5221,
        0.5147,
        0.5087,
        0.5072,
        0.5046,
        0.5027,
        0.4995,
        0.4929,
        0.4845,
        0.4683,
        0.4583,
        0.4484,
        0.4461,
        0.4445,
        0.4371,
        0.4172,
        0.3984,
        0.3819,
        0.376,
        0.3758,
        0.3849,
        0.3986,
        0.4168,
        0.4274,
        0.4364,
        0.4501,
        0.4695,
        0.4999,
        0.5394,
        0.5816,
        0.6213,
        0.6599,
        0.6824,
        0.7044,
        0.721,
        0.7335,
        0.7395,
        0.7466,
        0.7558,
        0.7585,
        0.7586,
        0.7584,
        0.762,
        0.7625,
        0.7614,
        0.7594,
        0.7533,
        0.7585,
        0.7607,
        0.7607,
        0.7625,
        0.7652,
        0.7688
    ]
}