{
    "name": "munsell/m_5R4_10",
    "type": "REFLECTANCE_NATURAL",
    "type_max": 1,
    "start_nm": 400,
    "end_nm": 700,
    "resolution": 5,
    "data": [
        0.0646,
        0.0633,
        0.0625,
        0.0631,
        0.0615,
        0.061,
        0.0602,
        0.0615,
        0.0621,
        0.0599,
        0.0609,
        0.0601,
        0.0595,
        0.0586,
        0.0563,
        0.0561,
        0.0559,
        0.0549,
        0.0534,
        0.0559,
        0.0558,
        0.0549,
        0.0555,
        0.054,
        0.055,
        0.056,
        0.0579,
        0.0612,
        0.0611,
        0.0639,
        0.0628,
        0.0651,
        0.0648,
        0.0689,
        0.0703,
        0.0751,
        0.0831,
        0.1,
        0.1244,
        0.1612,
        0.2049,
        0.2558,
        0.3055,
        0.3542,
        0.3963,
        0.4302,
        0.4533,
        0.4729,
        0.4833,
        0.4958,
        0.5009,
        0.5063,
        0.5124,
        0.5152,
        0.5214,
        0.5254,
        0.5272,
        0.532,
        0.5352,
        0.5388,
        0.5413
    ]
}