{
    "name": "munsell/m_5RP5_6",
    "type": "REFLECTANCE_NATURAL",
    "type_max": 1,
    "start_nm": 400,
    "end_nm": 700,
    "resolution": 5,
    "data": [
        0.1992,
        0.2075,
        0.2055,
        0.2044,
        0.2015,
        0.197,
        0.1952,
        0.1916,
        0.1903,
        0.1858,
        0.1842,
        0.1808,
        0.179,
        0.1799,
        0.1767,
        0.1727,
        0.1641,
        0.1564,
        0.1499,
        0.1435,
        0.1429,
        0.1416,
        0.1376,
        0.1308,
        0.1246,
        0.1135,
        0.1088,
        0.1107,
        0.1126,
        0.1203,
        0.1271,
        0.129,
        0.1303,
        0.1354,
        0.1428,
        0.1614,
        0.1839,
        0.2078,
        0.2315,
        0.2507,
        0.2664,
        0.2749,
        0.2839,
        0.2892,
        0.2898,
        0.2945,
        0.2955,
        0.2959,
        0.2979,
        0.2976,
        0.2975,
        0.2954,
        0.2975,
        0.2953,
        0.2958,
        0.2964,
        0.2938,
        0.2933,
        0.2964,
        0.2925,
        0.2907
    ]
}